yaag_mme/__init__.py
yaag_mme/cli.py
yaag_mme/yaag_mme.py
yaag_mme-0.0.1.dist-info/AUTHORS.md
yaag_mme-0.0.1.dist-info/LICENSE
yaag_mme-0.0.1.dist-info/METADATA
yaag_mme-0.0.1.dist-info/WHEEL
yaag_mme-0.0.1.dist-info/entry_points.txt
yaag_mme-0.0.1.dist-info/top_level.txt
yaag_mme-0.0.1.dist-info/RECORD
