Metadata-Version: 2.1
Name: yaag-mme
Version: 0.0.1
Summary: Yet Another Adventure Game - Murder Mystery Edition is a text based adventure game where you play with other NPC adventurers. But whether they live or die, is up to you.
Home-page: https://github.com/Cutewarriorlover/yaag-mme
Author: Cutewarriorlover
Author-email: cutewarriorlover@gmail.com
License: MIT license
Keywords: yaag_mme
Platform: UNKNOWN
Classifier: Development Status :: 2 - Pre-Alpha
Classifier: Intended Audience :: Other Audience
Classifier: License :: OSI Approved :: MIT License
Classifier: Natural Language :: English
Classifier: Environment :: Console
Classifier: Programming Language :: Python :: 3
Classifier: Programming Language :: Python :: 3.6
Classifier: Programming Language :: Python :: 3.7
Classifier: Programming Language :: Python :: 3.8
Classifier: Programming Language :: Python :: Implementation :: CPython
Requires-Python: >=3.6
License-File: LICENSE
License-File: AUTHORS.md
Requires-Dist: Click (>=7.0)
